Metadata-Version: 2.1
Name: lambda-debug-logging
Version: 0.1.0
Summary: Logging configuration to make debugging Lambdas easier
Home-page: https://github.com/vanguard/lambda-debug-logging
Author: Vanguard
Author-email: opensource@vanguard.com
License: Apache License 2.0
Platform: UNKNOWN
Classifier: Development Status :: 5 - Production/Stable
Classifier: Intended Audience :: Developers
Classifier: Natural Language :: English
Classifier: License :: OSI Approved :: Apache Software License
Classifier: Programming Language :: Python :: 3
Classifier: Programming Language :: Python :: 3.6
Classifier: Programming Language :: Python :: 3.7
Classifier: Programming Language :: Python :: 3.8
Classifier: Programming Language :: Python :: 3.9
Classifier: Programming Language :: Python :: 3.10
Classifier: Programming Language :: Python :: 3.11
